pyxel_helper/__init__.py
pyxel_helper/character_body.py
pyxel_helper/collision.py
pyxel_helper/engine.py
pyxel_helper/positioning.py
pyxel_helper/sprites.py
pyxel_helper-0.0.2.dist-info/METADATA
pyxel_helper-0.0.2.dist-info/WHEEL
pyxel_helper-0.0.2.dist-info/licenses/LICENSE
pyxel_helper-0.0.2.dist-info/RECORD
